{
    "KBHit":false,
    "binFileName":"pow_12873828219395495703_1",
    "binFileSuffix":".o",
    "blockDim":32,
    "coreType":"AiCore",
    "deterministic":"ignore",
    "globalworkspace_spec_workspace":{
        "size":32,
        "type":0
    },
    "kernelName":"pow_12873828219395495703_1__kernel0",
    "magic":"RT_DEV_BINARY_MAGIC_ELF",
    "memoryStamping":[],
    "opParaSize":0,
    "parameters":[
        null,
        null,
        null
    ],
    "sha256":"791cc1a0e3c6b88e575479385f6ea32568910c92cfbc62c3205a32caee2c0c82"
}